README.rst
setup.py
watchlist/__init__.py
watchlist/__main__.py
watchlist/compat.py
watchlist/email.py
watchlist/models.py
watchlist.egg-info/PKG-INFO
watchlist.egg-info/SOURCES.txt
watchlist.egg-info/dependency_links.txt
watchlist.egg-info/entry_points.txt
watchlist.egg-info/requires.txt
watchlist.egg-info/top_level.txt