Metadata-Version: 1.1
Name: watchlist
Version: 0.0.7
Summary: Amazon wishlist watcher
Home-page: http://github.com/Jaymon/watchlist
Author: Jay Marcyes
Author-email: jay@marcyes.com
License: GPLv2+
Platform: UNKNOWN
Classifier: Development Status :: 4 - Beta
Classifier: Environment :: Plugins
Classifier: Intended Audience :: Developers
Classifier: License :: OSI Approved :: GNU General Public License v2 or later (GPLv2+)
Classifier: Operating System :: OS Independent
Classifier: Programming Language :: Python :: 2.7
